slow_requests/__init__.py
slow_requests/examples.py
slow_requests/slow_requests.py
slow_requests-0.1.1.dist-info/LICENSE
slow_requests-0.1.1.dist-info/WHEEL
slow_requests-0.1.1.dist-info/METADATA
slow_requests-0.1.1.dist-info/RECORD
